{
  "type": "Feature",
  "properties": {
    "iso:country":"FI",
    "sg:address":"Urho Kekkosen katu 3 B",
    "sg:city":"Helsinki",
    "sg:classifiers":[
        {
            "category":"Manufacturing",
            "subcategory":"Electronics",
            "type":"Manufacturing & Wholesale Goods"
        }
    ],
    "sg:postcode":"00100 ",
    "sg:website":"http://www.nvidia.com",
    "wof:name":"NVidia",
    "wof:placetype":"venue"
},
  "geometry": {"coordinates":[24.932475,60.168546],"type":"Point"}
}