{
  "type": "Feature",
  "properties": {
    "iso:country":"FI",
    "sg:address":"Salmisaarenranta 7",
    "sg:city":"Helsinki",
    "sg:classifiers":[
        {
            "category":"Professional",
            "subcategory":"Computer Services",
            "type":"Services"
        }
    ],
    "sg:postcode":"00180",
    "sg:tags":[
        "mobile",
        "vas",
        "community",
        "social-networking",
        "connected-devices",
        "android",
        "tablets",
        "smartphones"
    ],
    "sg:website":"http://www.buongiorno.com",
    "wof:name":"Buongiorno",
    "wof:placetype":"venue"
},
  "geometry": {"coordinates":[24.899607,60.163748],"type":"Point"}
}