{
  "type": "Feature",
  "properties": {
    "iso:country":"FI",
    "sg:address":"Mannerheimintie 12 B 5th floor",
    "sg:city":"Helsinki",
    "sg:classifiers":[
        {
            "category":"Professional",
            "subcategory":"Computer Services",
            "type":"Services"
        }
    ],
    "sg:postcode":"00100",
    "sg:tags":[
        "multilingual",
        "social-networking",
        "games",
        "friends",
        "photos",
        "blogs",
        "realtime",
        "search"
    ],
    "sg:website":"http://www.xihalife.com/",
    "wof:name":"XIHA",
    "wof:placetype":"venue"
},
  "geometry": {"coordinates":[24.9410012,60.1681494],"type":"Point"}
}