{
  "type": "Feature",
  "properties": {
    "iso:country":"FI",
    "sg:address":"Museokatu 44",
    "sg:city":"Helsinki",
    "sg:classifiers":[
        {
            "category":"Professional",
            "subcategory":"Computer Services",
            "type":"Services"
        }
    ],
    "sg:postcode":"00100",
    "sg:tags":[
        "online",
        "video",
        "aggregator",
        "content"
    ],
    "sg:website":"http://www.videoflo.com",
    "wof:name":"Videoflow",
    "wof:placetype":"venue"
},
  "geometry": {"coordinates":[24.8144161,60.1842502],"type":"Point"}
}