{
  "type": "Feature",
  "properties": {
    "iso:country":"FI",
    "sg:address":"Keilalahdentie 2-4 P.O. Box 226, FIN-00045 Nokia Group",
    "sg:classifiers":[
        {
            "category":"Professional",
            "subcategory":"Computer Services",
            "type":"Services"
        }
    ],
    "sg:postcode":"FIN-00045",
    "sg:website":"http://nokia.com",
    "wof:name":"Nokia",
    "wof:placetype":"venue"
},
  "geometry": {"coordinates":[24.827224,60.170514],"type":"Point"}
}